vbiz_parser/__init__.py
vbiz_parser/ciddict.json
vbiz_parser/command_line.py
vbiz_parser/map.py
vbiz_parser-0.2.3.dist-info/LICENSE
vbiz_parser-0.2.3.dist-info/METADATA
vbiz_parser-0.2.3.dist-info/WHEEL
vbiz_parser-0.2.3.dist-info/entry_points.txt
vbiz_parser-0.2.3.dist-info/top_level.txt
vbiz_parser-0.2.3.dist-info/RECORD
