Metadata-Version: 2.1
Name: vbiz-parser
Version: 0.2.3
Summary: The vBiz parser
Home-page: https://github.com/ltdangkhoa/vbiz_parser
Author: Kris Luu
Author-email: luuthaidangkhoa@gmail.com
License: UNKNOWN
Platform: UNKNOWN
Classifier: Programming Language :: Python :: 3
Classifier: License :: OSI Approved :: MIT License
Classifier: Operating System :: OS Independent
Requires-Dist: pdfminer
